TextRandAug/__init__.py
TextRandAug/aeda.py
TextRandAug/augment.py
TextRandAug/eda.py
TextRandAug-0.0.4.dist-info/METADATA
TextRandAug-0.0.4.dist-info/WHEEL
TextRandAug-0.0.4.dist-info/top_level.txt
TextRandAug-0.0.4.dist-info/RECORD
