Metadata-Version: 2.1
Name: TextRandAug
Version: 0.0.4
Summary: We are highly thankful to Dr. Paul Buitelaar, Dr. Omnia Zayed, Dr. Mihael Arcan, Dr. John McCrae and Janet Choi. This module was built during 5th week CRT-AI training (NLP week) at National University of Ireland, Galway)
Home-page: UNKNOWN
Author: Jovan Jeromela,Liam De La Cour , Aaron Flannagan, Amandeep Singh and Teerath Kumar
Author-email: i141637@nu.edu.pk
License: UNKNOWN
Keywords: python,text data augmentation,random augmentation,randAug
Platform: UNKNOWN
Classifier: Development Status :: 1 - Planning
Classifier: Intended Audience :: Developers
Classifier: Programming Language :: Python :: 3
Classifier: Operating System :: Unix
Classifier: Operating System :: MacOS :: MacOS X
Classifier: Operating System :: Microsoft :: Windows
Requires-Dist: nltk
Requires-Dist: textaugment
